glone/__init__.py
glone/cli/__init__.py
glone/cli/constants.py
glone/cli/models.py
glone-0.3.0.dist-info/METADATA
glone-0.3.0.dist-info/WHEEL
glone-0.3.0.dist-info/entry_points.txt
glone-0.3.0.dist-info/licenses/LICENSE
glone-0.3.0.dist-info/RECORD
