Metadata-Version: 2.4
Name: glone
Version: 0.3.0
Summary: A CLI to back up all your GitHub repositories.
Project-URL: Issues, https://github.com/joaopalmeiro/glone/issues
Project-URL: Source, https://github.com/joaopalmeiro/glone
Author-email: João Palmeiro <joaopalmeiro@proton.me>
License-Expression: MIT
License-File: LICENSE
Classifier: Development Status :: 4 - Beta
Classifier: Environment :: Console
Classifier: Intended Audience :: Developers
Classifier: Intended Audience :: Information Technology
Classifier: Intended Audience :: Science/Research
Classifier: License :: OSI Approved :: MIT License
Classifier: Natural Language :: English
Classifier: Operating System :: OS Independent
Classifier: Programming Language :: Python
Classifier: Programming Language :: Python :: 3
Classifier: Programming Language :: Python :: 3 :: Only
Classifier: Programming Language :: Python :: 3.10
Classifier: Programming Language :: Python :: 3.11
Classifier: Programming Language :: Python :: 3.12
Classifier: Programming Language :: Python :: 3.13
Classifier: Programming Language :: Python :: Implementation :: CPython
Classifier: Topic :: Utilities
Requires-Python: >=3.10
Requires-Dist: click>=8.1.0
Requires-Dist: gaveta==0.6.0
Requires-Dist: httpx>=0.28.0
Requires-Dist: platformdirs>=4.0.0
Requires-Dist: pydantic>=2.11.0
Requires-Dist: trio>=0.29.0
